abstract_hardware_interface/__init__.py
abstract_hardware_interface/fan.py
abstract_hardware_interface/switches.py
abstract_hardware_interface/led/__init__.py
abstract_hardware_interface/led/animations.py
abstract_hardware_interface-0.0.2a1.dist-info/LICENSE.md
abstract_hardware_interface-0.0.2a1.dist-info/METADATA
abstract_hardware_interface-0.0.2a1.dist-info/WHEEL
abstract_hardware_interface-0.0.2a1.dist-info/top_level.txt
abstract_hardware_interface-0.0.2a1.dist-info/RECORD
