Metadata-Version: 2.1
Name: abstract-hardware-interface
Version: 0.0.2a1
Summary: Abstract Hardware Component Classes
Home-page: https://github.com/NeonGeckoCom/abstract-hardware-interface
Author: Neongecko
Author-email: developers@neon.ai
License: BSD-3
License-File: LICENSE.md
